redactive/__about__.py
redactive/__init__.py
redactive/_connection_mode.py
redactive/auth_client.py
redactive/multi_user_client.py
redactive/search_client.py
redactive/grpc/__init__.py
redactive/grpc/v2/__init__.py
redactive/reranking/__init__.py
redactive/reranking/reranker.py
redactive-2.0.1.dist-info/METADATA
redactive-2.0.1.dist-info/WHEEL
redactive-2.0.1.dist-info/RECORD
