Metadata-Version: 2.3
Name: redactive
Version: 2.0.1
Summary: Redactive Python SDK
Project-URL: Homepage, https://github.com/redactive-ai/redactive
Project-URL: Issues, https://github.com/redactive-ai/redactive/labels/sdk:python
Project-URL: Source, https://github.com/redactive-ai/redactive
Author-email: Redactive ai <support@redactive.ai>
Classifier: License :: OSI Approved :: MIT License
Classifier: Operating System :: OS Independent
Classifier: Programming Language :: Python :: 3
Classifier: Programming Language :: Python :: 3.11
Classifier: Programming Language :: Python :: 3.12
Requires-Python: >=3.11
Requires-Dist: betterproto[compiler]==2.0.0b6
Requires-Dist: grpclib[protobuf]
Requires-Dist: httpx
Requires-Dist: pydantic
Requires-Dist: pyjwt
Provides-Extra: reranking
Requires-Dist: rerankers; extra == 'reranking'
Requires-Dist: rerankers[transformers]; extra == 'reranking'
Provides-Extra: tests
Requires-Dist: pytest; extra == 'tests'
Requires-Dist: pytest-asyncio; extra == 'tests'
Requires-Dist: pytest-httpx; extra == 'tests'
